aivika_modeler-1.0.0.dist-info/DESCRIPTION.rst
aivika_modeler-1.0.0.dist-info/METADATA
aivika_modeler-1.0.0.dist-info/RECORD
aivika_modeler-1.0.0.dist-info/WHEEL
aivika_modeler-1.0.0.dist-info/metadata.json
aivika_modeler-1.0.0.dist-info/top_level.txt
simulation/__init__.py
simulation/aivika/__init__.py
simulation/aivika/modeler/__init__.py
simulation/aivika/modeler/arrival_timer.py
simulation/aivika/modeler/data_type.py
simulation/aivika/modeler/expr.py
simulation/aivika/modeler/expr_random.py
simulation/aivika/modeler/expr_run.py
simulation/aivika/modeler/model.py
simulation/aivika/modeler/model_project.py
simulation/aivika/modeler/pdf.py
simulation/aivika/modeler/port.py
simulation/aivika/modeler/queue.py
simulation/aivika/modeler/queue_strategy.py
simulation/aivika/modeler/ref.py
simulation/aivika/modeler/resource.py
simulation/aivika/modeler/resource_preemption.py
simulation/aivika/modeler/results.py
simulation/aivika/modeler/server.py
simulation/aivika/modeler/server_random.py
simulation/aivika/modeler/specs.py
simulation/aivika/modeler/stats.py
simulation/aivika/modeler/stream.py
simulation/aivika/modeler/stream_random.py
simulation/aivika/modeler/transform.py
simulation/aivika/modeler/util.py
simulation/aivika/modeler/experiment/__init__.py
simulation/aivika/modeler/experiment/experiment.py
simulation/aivika/modeler/experiment/experiment_renderer.py
simulation/aivika/modeler/experiment/base/__init__.py
simulation/aivika/modeler/experiment/base/experiment_specs.py
simulation/aivika/modeler/experiment/base/final_stats.py
simulation/aivika/modeler/experiment/base/final_table.py
simulation/aivika/modeler/experiment/base/info.py
simulation/aivika/modeler/experiment/base/last_value.py
simulation/aivika/modeler/experiment/base/table.py
simulation/aivika/modeler/experiment/base/timing_stats.py
simulation/aivika/modeler/experiment/base/types.py
simulation/aivika/modeler/experiment/chart/__init__.py
simulation/aivika/modeler/experiment/chart/deviation_chart.py
simulation/aivika/modeler/experiment/chart/final_histogram.py
simulation/aivika/modeler/experiment/chart/final_xy_chart.py
simulation/aivika/modeler/experiment/chart/histogram.py
