Metadata-Version: 2.0
Name: aivika-modeler
Version: 1.0.0
Summary: A discrete event simulation modeling tool
Home-page: https://github.com/dsorokin/aivika-modeler
Author: David E. Sorokin
Author-email: david.sorokin@gmail.com
License: BSD3
Keywords: simulation,discrete event simulation,simulation library,queue network
Platform: UNKNOWN
Classifier: Development Status :: 4 - Beta
Classifier: Intended Audience :: Developers
Classifier: Intended Audience :: Science/Research
Classifier: Topic :: Scientific/Engineering
Classifier: License :: OSI Approved :: BSD License
Classifier: Programming Language :: Python :: 2
Classifier: Programming Language :: Python :: 2.7
Classifier: Programming Language :: Python :: 3
Classifier: Programming Language :: Python :: 3.3
Classifier: Programming Language :: Python :: 3.4
Classifier: Programming Language :: Python :: 3.5
